LICENSE
MANIFEST.in
README.md
setup.py
pyPhasesRecordloaderPhysionet/Plugin.py
pyPhasesRecordloaderPhysionet/__init__.py
pyPhasesRecordloaderPhysionet/config.yaml
pyPhasesRecordloaderPhysionet.egg-info/PKG-INFO
pyPhasesRecordloaderPhysionet.egg-info/SOURCES.txt
pyPhasesRecordloaderPhysionet.egg-info/dependency_links.txt
pyPhasesRecordloaderPhysionet.egg-info/requires.txt
pyPhasesRecordloaderPhysionet.egg-info/top_level.txt
pyPhasesRecordloaderPhysionet/recordLoaders/RecordLoaderPhysio.py
pyPhasesRecordloaderPhysionet/recordLoaders/__init__.py